stats/__init__.py
stats/astrophotography_stats.py
stats/cache_handler.py
stats/detailed_panel_stats.py
stats/session_stats.py
stats/stats.py
mosaic_stats-0.1.3.dist-info/LICENSE
mosaic_stats-0.1.3.dist-info/METADATA
mosaic_stats-0.1.3.dist-info/WHEEL
mosaic_stats-0.1.3.dist-info/entry_points.txt
mosaic_stats-0.1.3.dist-info/top_level.txt
mosaic_stats-0.1.3.dist-info/RECORD
