Metadata-Version: 2.1
Name: mosaic-stats
Version: 0.1.3
Summary: Statistics generation script for astrophotography mosaic projects
Home-page: https://github.com/kdzuin/mosaic-stats
Author: Konstantin Dziuin
Author-email: kdzuin@gmail.com
License: UNKNOWN
Platform: UNKNOWN
Classifier: Programming Language :: Python :: 3
Classifier: License :: OSI Approved :: MIT License
Classifier: Operating System :: OS Independent
Requires-Python: >=3.6
License-File: LICENSE
Requires-Dist: astropy
